hatch_pyz/__init__.py
hatch_pyz/builder.py
hatch_pyz/config.py
hatch_pyz/hooks.py
hatch_pyz/py.typed
hatch_pyz-0.3.0.dist-info/METADATA
hatch_pyz-0.3.0.dist-info/WHEEL
hatch_pyz-0.3.0.dist-info/entry_points.txt
hatch_pyz-0.3.0.dist-info/licenses/LICENSE
hatch_pyz-0.3.0.dist-info/RECORD
