Metadata-Version: 2.3
Name: hatch-pyz
Version: 0.3.0
Summary: Hatch plugin for building python zip applications
Project-URL: Homepage, https://github.com/djcopley/hatch-pyz
Project-URL: Repository, https://github.com/djcopley/hatch-pyz.git
Project-URL: Issues, https://github.com/djcopley/hatch-pyz/issues
Author-email: Daniel Copley <djcopley@proton.me>
License-File: LICENSE
Keywords: hatch,plugin,pyz
Classifier: Framework :: Hatch
Classifier: Programming Language :: Python
Classifier: Programming Language :: Python :: 3.8
Classifier: Programming Language :: Python :: 3.9
Classifier: Programming Language :: Python :: 3.10
Classifier: Programming Language :: Python :: 3.11
Classifier: Programming Language :: Python :: 3.12
Requires-Python: >=3.8
Requires-Dist: hatchling~=1.25
Requires-Dist: pip~=24.0
Requires-Dist: typing-extensions~=4.0; python_version < '3.10'
